manim_express/.gitignore
manim_express/__init__.py
manim_express/color.py
manim_express/custom_config.yml
manim_express/eager.py
manim_express/hand_draw.py
manim_express/points.py
manim_express/version-config.yaml
manim_express/backend/__init__.py
manim_express/backend/tick.py
manim_express/backend/manimce/.gitignore
manim_express/backend/manimce/__init__.py
manim_express/backend/manimce/eager.py
manim_express/backend/manimgl/__init__.py
manim_express/backend/manimgl/config.py
manim_express/backend/manimgl/express/__init__.py
manim_express/backend/manimgl/express/coordinate_sys.py
manim_express/backend/manimgl/express/custom_config.yml
manim_express/backend/manimgl/express/eager.py
manim_express/backend/manimgl/express/plot.py
manim_express/backend/manimgl/express/scatter.py
manim_express/backend/manimgl/express/surface.py
manim_express/backend/manimgl/mobject/__init__.py
manim_express/backend/manimgl/mobject/geometry.py
manim_express/backend/manimgl/scene/__init__.py
manim_express/backend/manimgl/scene/scene.py
manim_express/backend/manimgl/utils/__init__.py
manim_express/backend/manimgl/utils/code.py
manim_express/interest/__init__.py
manim_express/interest/string_art.py
manim_express/math/__init__.py
manim_express/math/quaternion.py
manim_express/math/vec.py
manim_express/nn/__init__.py
manim_express/nn/network.py
manim_express/utils/__init__.py
manim_express/utils/jupyter.py
manim_express/utils/onlinetex.py
manim_express/utils/tools.py
manim_express/video/__init__.py
manim_express/video/load.py
manim_express-0.6.8.data/data/manim_express/.gitignore
manim_express-0.6.8.data/data/manim_express/__init__.py
manim_express-0.6.8.data/data/manim_express/color.py
manim_express-0.6.8.data/data/manim_express/custom_config.yml
manim_express-0.6.8.data/data/manim_express/eager.py
manim_express-0.6.8.data/data/manim_express/hand_draw.py
manim_express-0.6.8.data/data/manim_express/points.py
manim_express-0.6.8.data/data/manim_express/version-config.yaml
manim_express-0.6.8.dist-info/AUTHORS
manim_express-0.6.8.dist-info/LICENSE
manim_express-0.6.8.dist-info/METADATA
manim_express-0.6.8.dist-info/WHEEL
manim_express-0.6.8.dist-info/entry_points.txt
manim_express-0.6.8.dist-info/pbr.json
manim_express-0.6.8.dist-info/top_level.txt
manim_express-0.6.8.dist-info/RECORD
