Metadata-Version: 2.1
Name: manim-express
Version: 0.6.8
Summary: Animation engine for explanatory math videos
Home-page: https://github.com/beidongjiedeguang/manim-express
Author: kunyuan
Author-email: beidongjiedeguang@gmail.com
License: MIT
Project-URL: Bug Tracker, https://github.com/beidongjiedeguang/manim-express/issues
Project-URL: Source Code, https://github.com/beidongjiedeguang/manim-express
Keywords: Computer Vision,Mathematics,Physics,Machine Learning,Neural Networks
Platform: UNKNOWN
Classifier: Operating System :: OS Independent
Classifier: Intended Audience :: Developers
Classifier: Intended Audience :: Science/Research
Classifier: Topic :: Scientific/Engineering :: Artificial Intelligence
Classifier: Programming Language :: Python :: 3
Classifier: Programming Language :: Python :: 3.8
Requires-Python: >=3.7
License-File: LICENSE
License-File: AUTHORS
Requires-Dist: manimgl (>=1.5.0)
Requires-Dist: manim (>=0.15.0)
Requires-Dist: sparrow-tool (>=0.3.13)
Requires-Dist: fake-headers
Requires-Dist: requests
Requires-Dist: PyOpenGL-accelerate
Provides-Extra: dev
Requires-Dist: pyperclip ; extra == 'dev'
Requires-Dist: manim-rubikscube ; extra == 'dev'
Requires-Dist: manim-physics (>=0.2.3) ; extra == 'dev'
Requires-Dist: manim-editor ; extra == 'dev'
